odoo8_addon_website_blog_title_image-8.0.1.0.0.99.dev10-py2.7-nspkg.pth
odoo8_addon_website_blog_title_image-8.0.1.0.0.99.dev10.dist-info/METADATA
odoo8_addon_website_blog_title_image-8.0.1.0.0.99.dev10.dist-info/RECORD
odoo8_addon_website_blog_title_image-8.0.1.0.0.99.dev10.dist-info/WHEEL
odoo8_addon_website_blog_title_image-8.0.1.0.0.99.dev10.dist-info/namespace_packages.txt
odoo8_addon_website_blog_title_image-8.0.1.0.0.99.dev10.dist-info/top_level.txt
odoo_addons/website_blog_title_image/README.rst
odoo_addons/website_blog_title_image/__init__.py
odoo_addons/website_blog_title_image/__openerp__.py
odoo_addons/website_blog_title_image/i18n/bg.po
odoo_addons/website_blog_title_image/i18n/de.po
odoo_addons/website_blog_title_image/i18n/el_GR.po
odoo_addons/website_blog_title_image/i18n/es.po
odoo_addons/website_blog_title_image/i18n/eu.po
odoo_addons/website_blog_title_image/i18n/fr.po
odoo_addons/website_blog_title_image/i18n/it.po
odoo_addons/website_blog_title_image/i18n/pt_BR.po
odoo_addons/website_blog_title_image/i18n/sl.po
odoo_addons/website_blog_title_image/i18n/website_blog_title_image.pot
odoo_addons/website_blog_title_image/models/__init__.py
odoo_addons/website_blog_title_image/models/website_blog.py
odoo_addons/website_blog_title_image/static/description/icon.png
odoo_addons/website_blog_title_image/views/blog_post_view.xml
odoo_addons/website_blog_title_image/views/website_blog_templates.xml
